Metadata-Version: 2.4
Name: iflow-mcp_sshtunnelvision_mcp-tool-server
Version: 0.1.0
Summary: Add your description here
Requires-Python: >=3.13
License-File: LICENSE
Requires-Dist: fal-client>=0.5.9
Requires-Dist: fastapi>=0.115.11
Requires-Dist: mcp[cli]>=1.3.0
Requires-Dist: python-dotenv>=1.0.1
Requires-Dist: sse-starlette>=2.2.1
Requires-Dist: uvicorn>=0.34.0
Requires-Dist: Pillow>=10.0.0
Dynamic: license-file
